{
	"id": "dill0yKInmsFxAu",
	"json": "{\"id\":\"dill0yKInmsFxAu\",\"url\":\"https://techblog.woowahan.com/25049/\",\"loadedUrl\":\"https://techblog.woowahan.com/25049/\",\"uniqueKey\":\"https://techblog.woowahan.com/25049\",\"method\":\"GET\",\"noRetry\":false,\"retryCount\":0,\"errorMessages\":[],\"headers\":{},\"userData\":{\"url\":\"https://techblog.woowahan.com/25049/\",\"title\":\"끊김 없는 사용 경험을 위하여 : 카카오톡 선물함 속 교환권을 배달의민족 주문으로 연결한 여정\",\"pubDate\":\"2025-12-26T06:00:42.000Z\",\"source\":\"우아한형제들 기술블로그\",\"sourceId\":\"feed-mjnqz2w\",\"category\":\"dev-blog\",\"tags\":[\"Frontend\",\"PM\"],\"guid\":\"https://techblog.woowa.in/?p=25049\",\"imageUrlFromRss\":\"https://techblog.woowa.in/wp-content/uploads/2025/12/%EC%8A%A4%ED%81%AC%EB%A6%B0%EC%83%B7-2025-12-14-%EC%98%A4%ED%9B%84-5.26.35-750x153.png\",\"__crawlee\":{\"state\":4}},\"handledAt\":\"2026-01-05T00:44:17.621Z\"}",
	"method": "GET",
	"orderNo": null,
	"retryCount": 0,
	"uniqueKey": "https://techblog.woowahan.com/25049",
	"url": "https://techblog.woowahan.com/25049/"
}