{
	"id": "lOYG3XTqGQEc56y",
	"json": "{\"id\":\"lOYG3XTqGQEc56y\",\"url\":\"https://blog.opensurvey.co.kr/article/webinar-eat-2025-1/\",\"loadedUrl\":\"https://blog.opensurvey.co.kr/article/webinar-eat-2025-1/\",\"uniqueKey\":\"https://blog.opensurvey.co.kr/article/webinar-eat-2025-1\",\"method\":\"GET\",\"noRetry\":false,\"retryCount\":0,\"errorMessages\":[],\"headers\":{},\"userData\":{\"url\":\"https://blog.opensurvey.co.kr/article/webinar-eat-2025-1/\",\"title\":\"2026 식생활 트렌드: 물가와 건강 다 잡는 ‘집밥’ 열풍, 뜨는 메뉴 TOP 5\",\"pubDate\":\"2025-12-03T00:30:00.000Z\",\"source\":\"오픈서베이 블로그\",\"sourceId\":\"feed-3p1eoj2\",\"category\":\"it-trend\",\"tags\":[\"Article\",\"FEATURED POST\",\"Eat\",\"EatBuyPlay\"],\"guid\":\"https://blog.opensurvey.co.kr/?p=36238\",\"imageUrlFromRss\":null,\"__crawlee\":{\"state\":4}},\"handledAt\":\"2026-01-05T00:48:57.999Z\"}",
	"method": "GET",
	"orderNo": null,
	"retryCount": 0,
	"uniqueKey": "https://blog.opensurvey.co.kr/article/webinar-eat-2025-1",
	"url": "https://blog.opensurvey.co.kr/article/webinar-eat-2025-1/"
}