{
	"id": "oKIdFhPM8xulE1T",
	"json": "{\"id\":\"oKIdFhPM8xulE1T\",\"url\":\"https://blog.opensurvey.co.kr/news/trendreport-2026-trend-1/\",\"loadedUrl\":\"https://blog.opensurvey.co.kr/news/trendreport-2026-trend-1/\",\"uniqueKey\":\"https://blog.opensurvey.co.kr/news/trendreport-2026-trend-1\",\"method\":\"GET\",\"noRetry\":false,\"retryCount\":0,\"errorMessages\":[],\"headers\":{},\"userData\":{\"url\":\"https://blog.opensurvey.co.kr/news/trendreport-2026-trend-1/\",\"title\":\"오픈서베이 트렌드 리포트로 본 2026년 트렌드 전망: 액티브 시니어, AI 에이전트, 그리고 초개인화\",\"pubDate\":\"2025-12-22T01:43:29.000Z\",\"source\":\"오픈서베이 블로그\",\"sourceId\":\"feed-3p1eoj2\",\"category\":\"it-trend\",\"tags\":[\"News\",\"Article\",\"트렌드리포트결산\",\"오픈서베이 트렌드 리포트\"],\"guid\":\"https://blog.opensurvey.co.kr/?p=36447\",\"imageUrlFromRss\":null,\"__crawlee\":{\"state\":4}},\"handledAt\":\"2026-01-05T00:48:49.843Z\"}",
	"method": "GET",
	"orderNo": null,
	"retryCount": 0,
	"uniqueKey": "https://blog.opensurvey.co.kr/news/trendreport-2026-trend-1",
	"url": "https://blog.opensurvey.co.kr/news/trendreport-2026-trend-1/"
}