{
	"id": "vd3rvYSFfuV370p",
	"json": "{\"id\":\"vd3rvYSFfuV370p\",\"url\":\"https://lemondesign.tistory.com/100\",\"loadedUrl\":\"https://lemondesign.tistory.com/100\",\"uniqueKey\":\"https://lemondesign.tistory.com/100\",\"method\":\"GET\",\"noRetry\":false,\"retryCount\":0,\"errorMessages\":[],\"headers\":{},\"userData\":{\"url\":\"https://lemondesign.tistory.com/100\",\"title\":\"세계 최대 고해상도 영화 이미지 사이트!\",\"pubDate\":\"2023-12-14T12:18:38.000Z\",\"source\":\"레몬디자인\",\"sourceId\":\"feed-f5wipgj\",\"category\":\"-ux\",\"tags\":[\"디자인/디자인 사이트\"],\"guid\":\"https://lemondesign.tistory.com/100\",\"imageUrlFromRss\":null,\"__crawlee\":{\"state\":4}},\"handledAt\":\"2026-01-05T00:43:04.606Z\"}",
	"method": "GET",
	"orderNo": null,
	"retryCount": 0,
	"uniqueKey": "https://lemondesign.tistory.com/100",
	"url": "https://lemondesign.tistory.com/100"
}